[
  {
    "codigo": 1,
    "nome": "Acompanhamentos",
    "descricao": "Manteiga, nata, mel, requeijão salgado, queijo branco.",
    "preco": 27.56,
    "peso": 160,
    "foto": "cafe1.jpg",
    "desconto": 0,
    "pontosDasAvaliacoes": 4,
    "totalDeAvaliacoes": 350,
    "disponibilidade": 5,
    "totalDeCompras": 0,
    "ehVegetariano": false,
    "categoria": 1
  },
  {
    "codigo": 2,
    "nome": "Bruschetta de salmão e abacate",
    "descricao": "Pão preto, salmão defumado, queijo Philadelphia, abacate, tomate, ovos.",
    "preco": 52.49,
    "peso": 180,
    "foto": "cafe2.jpg",
    "desconto": 10,
    "pontosDasAvaliacoes": 4,
    "totalDeAvaliacoes": 320,
    "disponibilidade": 7,
    "totalDeCompras": 0,
    "ehVegetariano": false,
    "categoria": 1
  },
  {
    "codigo": 3,
    "nome": "Croque Madame",
    "descricao": "Pão torrado, salame de vitela, ovos, manteiga, queijo, rúcula, cenoura, pepino, rabanete.",
    "preco": 35.1,
    "peso": 125,
    "foto": "cafe3.jpg",
    "desconto": 0,
    "pontosDasAvaliacoes": 4,
    "totalDeAvaliacoes": 370,
    "disponibilidade": 5,
    "totalDeCompras": 0,
    "ehVegetariano": false,
    "categoria": 1
  },
  {
    "codigo": 4,
    "nome": "Panquecas de queijo",
    "descricao": "Folhada, recheio de queijo, rúcula, cenoura, pepino, rabanete.",
    "preco": 32.34,
    "peso": 110,
    "foto": "cafe4.jpg",
    "desconto": 0,
    "pontosDasAvaliacoes": 4,
    "totalDeAvaliacoes": 380,
    "disponibilidade": 7,
    "totalDeCompras": 0,
    "ehVegetariano": false,
    "categoria": 1
  },
  {
    "codigo": 5,
    "nome": "Sanduíche de queijo",
    "descricao": "Pão torrado, queijo cheddar, queijo gouda, manteiga, rúcula, cenoura, pepino, rabanete.",
    "preco": 22.34,
    "peso": 110,
    "foto": "cafe5.jpg",
    "desconto": 0,
    "pontosDasAvaliacoes": 5,
    "totalDeAvaliacoes": 480,
    "disponibilidade": 7,
    "totalDeCompras": 0,
    "ehVegetariano": false,
    "categoria": 1
  },
  {
    "codigo": 6,
    "nome": "Sanduíche de torrada escura",
    "descricao": "Pão escuro, presunto, ovos, queijo gouda, rúcula, cenoura, pepino, rabanete.",
    "preco": 28.14,
    "peso": 170,
    "foto": "cafe6.jpg",
    "desconto": 0,
    "pontosDasAvaliacoes": 4,
    "totalDeAvaliacoes": 380,
    "disponibilidade": 6,
    "totalDeCompras": 0,
    "ehVegetariano": false,
    "categoria": 1
  },
  {
    "codigo": 7,
    "nome": "Omelete misto",
    "descricao": "Salada de ovos, filé de frango, queijo gouda, rúcula e tomate.",
    "preco": 25.1,
    "peso": 170,
    "foto": "cafe7.jpg",
    "desconto": 10,
    "pontosDasAvaliacoes": 4,
    "totalDeAvaliacoes": 380,
    "disponibilidade": 6,
    "totalDeCompras": 0,
    "ehVegetariano": false,
    "categoria": 1
  },
  {
    "codigo": 8,
    "nome": "Prato de queijo",
    "descricao": "Queijo de leite de ovelha, queijo motal, requeijão, queijo branco.",
    "preco": 20.3,
    "peso": 170,
    "foto": "aperitivo1.jpg",
    "desconto": 0,
    "pontosDasAvaliacoes": 4,
    "totalDeAvaliacoes": 380,
    "disponibilidade": 6,
    "totalDeCompras": 0,
    "ehVegetariano": false,
    "categoria": 2
  },
  {
    "codigo": 9,
    "nome": "Frios",
    "descricao": "Linguicinha, rolinho de frango, basturma de vitela.",
    "preco": 25.82,
    "peso": 120,
    "foto": "aperitivo2.jpg",
    "desconto": 0,
    "pontosDasAvaliacoes": 4,
    "totalDeAvaliacoes": 380,
    "disponibilidade": 6,
    "totalDeCompras": 0,
    "ehVegetariano": false,
    "categoria": 2
  },
  {
    "codigo": 10,
    "nome": "Berinjelas ao estilo oriental",
    "descricao": "Berinjelas, nozes, curry, creme de leite, alho.",
    "preco": 19.44,
    "peso": 145,
    "foto": "aperitivo3.jpg",
    "desconto": 0,
    "pontosDasAvaliacoes": 4,
    "totalDeAvaliacoes": 380,
    "disponibilidade": 6,
    "totalDeCompras": 0,
    "ehVegetariano": false,
    "categoria": 2
  },
  {
    "codigo": 11,
    "nome": "Lanche especial de berinjelas",
    "descricao": "Berinjela marinada, molho especial, verduras.",
    "preco": 21.9,
    "peso": 120,
    "foto": "aperitivo4.jpg",
    "desconto": 10,
    "pontosDasAvaliacoes": 3,
    "totalDeAvaliacoes": 280,
    "disponibilidade": 8,
    "totalDeCompras": 0,
    "ehVegetariano": true,
    "categoria": 2
  },
  {
    "codigo": 12,
    "nome": "Tomates marinados em vinagre",
    "descricao": "Tomate, vinagre de uva, salsa, sementes de abóbora, azeite, alho.",
    "preco": 12.62,
    "peso": 120,
    "foto": "aperitivo5.jpg",
    "desconto": 0,
    "pontosDasAvaliacoes": 3,
    "totalDeAvaliacoes": 280,
    "disponibilidade": 8,
    "totalDeCompras": 0,
    "ehVegetariano": true,
    "categoria": 2
  },
  {
    "codigo": 13,
    "nome": "Petisco de batata",
    "descricao": "Batata, queijo branco, queijo motal, tomate seco, queijo gouda, azeite, alho.",
    "preco": 17.84,
    "peso": 120,
    "foto": "aperitivo6.jpg",
    "desconto": 0,
    "pontosDasAvaliacoes": 3,
    "totalDeAvaliacoes": 280,
    "disponibilidade": 8,
    "totalDeCompras": 0,
    "ehVegetariano": true,
    "categoria": 2
  },
  {
    "codigo": 14,
    "nome": "Salada de berinjela",
    "descricao": "Berinjela, tomate, pimentão, pimentão, óleo de milho, alho, verduras frescas.",
    "preco": 23.5,
    "peso": 120,
    "foto": "salada1.jpg",
    "desconto": 0,
    "pontosDasAvaliacoes": 3,
    "totalDeAvaliacoes": 280,
    "disponibilidade": 8,
    "totalDeCompras": 0,
    "ehVegetariano": true,
    "categoria": 3
  },
  {
    "codigo": 15,
    "nome": "Salada Russa",
    "descricao": "Carne, batata, cenoura, ovos, pepino fresco, pepino em conserva, maionese, ervilha.",
    "preco": 25.1,
    "peso": 120,
    "foto": "salada2.jpg",
    "desconto": 0,
    "pontosDasAvaliacoes": 3,
    "totalDeAvaliacoes": 280,
    "disponibilidade": 8,
    "totalDeCompras": 0,
    "ehVegetariano": false,
    "categoria": 3
  },
  {
    "codigo": 16,
    "nome": "Salada crocante de berinjela",
    "descricao": "Berinjelas, tomates, molho de ostra, sementes de gergelim branco.",
    "preco": 27.56,
    "peso": 130,
    "foto": "salada3.jpg",
    "desconto": 0,
    "pontosDasAvaliacoes": 3,
    "totalDeAvaliacoes": 280,
    "disponibilidade": 8,
    "totalDeCompras": 0,
    "ehVegetariano": true,
    "categoria": 3
  },
  {
    "codigo": 17,
    "nome": "Sopa de frango com arroz",
    "descricao": "Frango, arroz redondo, cebola, cenoura, ameixa cereja, cúrcuma.",
    "preco": 27.56,
    "peso": 130,
    "foto": "sopa1.jpg",
    "desconto": 10,
    "pontosDasAvaliacoes": 4,
    "totalDeAvaliacoes": 480,
    "disponibilidade": 8,
    "totalDeCompras": 0,
    "ehVegetariano": false,
    "categoria": 4
  },
  {
    "codigo": 18,
    "nome": "Sopa de macarrão com almôndegas",
    "descricao": "Macarrão caseiro, vitela, caldo de carne, cebola, cenoura, açafrão, feijão mungo.",
    "preco": 26.69,
    "peso": 180,
    "foto": "sopa2.jpg",
    "desconto": 0,
    "pontosDasAvaliacoes": 4,
    "totalDeAvaliacoes": 480,
    "disponibilidade": 5,
    "totalDeCompras": 0,
    "ehVegetariano": false,
    "categoria": 4
  },
  {
    "codigo": 19,
    "nome": "Sopa de cebola",
    "descricao": "Cebola, farinha de trigo, batata, ovos, coentro, manteiga.",
    "preco": 23.5,
    "peso": 150,
    "foto": "sopa3.jpg",
    "desconto": 0,
    "pontosDasAvaliacoes": 4,
    "totalDeAvaliacoes": 480,
    "disponibilidade": 5,
    "totalDeCompras": 0,
    "ehVegetariano": false,
    "categoria": 4
  },
  {
    "codigo": 20,
    "nome": "Filé mignon com batata",
    "descricao": "Filé mignon, manteiga, pimenta do reino, tomate, batata.",
    "preco": 57.29,
    "peso": 220,
    "foto": "carne1.jpg",
    "desconto": 0,
    "pontosDasAvaliacoes": 4,
    "totalDeAvaliacoes": 480,
    "disponibilidade": 5,
    "totalDeCompras": 0,
    "ehVegetariano": false,
    "categoria": 5
  },
  {
    "codigo": 21,
    "nome": "Dolma do Azerbaijão",
    "descricao": "Vitela, borrego, beringela, tomate, pimentão.",
    "preco": 51.49,
    "peso": 230,
    "foto": "carne2.jpg",
    "desconto": 0,
    "pontosDasAvaliacoes": 4,
    "totalDeAvaliacoes": 480,
    "disponibilidade": 5,
    "totalDeCompras": 0,
    "ehVegetariano": false,
    "categoria": 5
  },
  {
    "codigo": 22,
    "nome": "Fritas com Carne",
    "descricao": "Massa, vitela, rabo gordo, verduras frescas.",
    "preco": 39.89,
    "peso": 170,
    "foto": "carne3.jpg",
    "desconto": 10,
    "pontosDasAvaliacoes": 4,
    "totalDeAvaliacoes": 480,
    "disponibilidade": 5,
    "totalDeCompras": 0,
    "ehVegetariano": false,
    "categoria": 5
  },
  {
    "codigo": 23,
    "nome": "Vitela com cogumelos em molho picante",
    "descricao": "Vitela, cogumelos, manteiga, molho de pimenta doce, cebola, coentro.",
    "preco": 35.69,
    "peso": 180,
    "foto": "carne4.jpg",
    "desconto": 0,
    "pontosDasAvaliacoes": 4,
    "totalDeAvaliacoes": 480,
    "disponibilidade": 5,
    "totalDeCompras": 0,
    "ehVegetariano": false,
    "categoria": 5
  },
  {
    "codigo": 24,
    "nome": "Tabaka de frango",
    "descricao": "Frango para duas pessoas",
    "preco": 28.29,
    "peso": 150,
    "foto": "frango1.jpg",
    "desconto": 20,
    "pontosDasAvaliacoes": 4,
    "totalDeAvaliacoes": 480,
    "disponibilidade": 5,
    "totalDeCompras": 0,
    "ehVegetariano": false,
    "categoria": 6
  },
  {
    "codigo": 25,
    "nome": "Filé de frango com batata",
    "descricao": "Filé de frango, batata, tomate",
    "preco": 22.49,
    "peso": 140,
    "foto": "frango2.jpg",
    "desconto": 0,
    "pontosDasAvaliacoes": 4,
    "totalDeAvaliacoes": 480,
    "disponibilidade": 5,
    "totalDeCompras": 0,
    "ehVegetariano": false,
    "categoria": 6
  },
  {
    "codigo": 26,
    "nome": "Frango árabe",
    "descricao": "Frango, cebola, tomate, pimentão, berinjela, batata.",
    "preco": 27.29,
    "peso": 230,
    "foto": "frango3.jpg",
    "desconto": 0,
    "pontosDasAvaliacoes": 4,
    "totalDeAvaliacoes": 480,
    "disponibilidade": 5,
    "totalDeCompras": 0,
    "ehVegetariano": false,
    "categoria": 6
  },
  {
    "codigo": 27,
    "nome": "Frutas da estação",
    "descricao": "Maçã, pêssego, morango, melão e uvas.",
    "preco": 15.1,
    "peso": 250,
    "foto": "sobremesa1.jpg",
    "desconto": 10,
    "pontosDasAvaliacoes": 4,
    "totalDeAvaliacoes": 480,
    "disponibilidade": 5,
    "totalDeCompras": 0,
    "ehVegetariano": false,
    "categoria": 7
  },
  {
    "codigo": 28,
    "nome": "Geléia",
    "descricao": "Geléia de amoras, morango e pêssego.",
    "preco": 21.33,
    "peso": 150,
    "foto": "sobremesa2.jpg",
    "desconto": 0,
    "pontosDasAvaliacoes": 4,
    "totalDeAvaliacoes": 480,
    "disponibilidade": 5,
    "totalDeCompras": 0,
    "ehVegetariano": false,
    "categoria": 7
  },
  {
    "codigo": 29,
    "nome": "Variedade de frutas secas e nozes",
    "descricao": "Castanhas, damasco, uvas secas e nozes",
    "preco": 19.3,
    "peso": 150,
    "foto": "sobremesa3.jpg",
    "desconto": 0,
    "pontosDasAvaliacoes": 4,
    "totalDeAvaliacoes": 480,
    "disponibilidade": 5,
    "totalDeCompras": 0,
    "ehVegetariano": false,
    "categoria": 7
  },
  {
    "codigo": 30,
    "nome": "Sorvete",
    "descricao": "Sorvete de morango.",
    "preco": 14.09,
    "peso": 150,
    "foto": "sobremesa4.jpg",
    "desconto": 0,
    "pontosDasAvaliacoes": 4,
    "totalDeAvaliacoes": 480,
    "disponibilidade": 5,
    "totalDeCompras": 0,
    "ehVegetariano": false,
    "categoria": 7
  },
  {
    "codigo": 31,
    "nome": "Vinho tinto",
    "descricao": "Vinho tinto seco, francês.",
    "preco": 47.89,
    "peso": 250,
    "foto": "bebida1.jpg",
    "desconto": 0,
    "pontosDasAvaliacoes": 4,
    "totalDeAvaliacoes": 480,
    "disponibilidade": 5,
    "totalDeCompras": 0,
    "ehVegetariano": false,
    "categoria": 8
  },
  {
    "codigo": 32,
    "nome": "Cerveja Pilsen",
    "descricao": "Caneco de cerveja Pilsen de 500ml.",
    "preco": 11.9,
    "peso": 170,
    "foto": "bebida2.jpg",
    "desconto": 10,
    "pontosDasAvaliacoes": 4,
    "totalDeAvaliacoes": 480,
    "disponibilidade": 5,
    "totalDeCompras": 0,
    "ehVegetariano": false,
    "categoria":8
  },
  {
    "codigo": 33,
    "nome": "Xícara de chá",
    "descricao": "Xícara de chá de ervas egípcias.",
    "preco": 5.34,
    "peso": 150,
    "foto": "bebida3.jpg",
    "desconto": 0,
    "pontosDasAvaliacoes": 4,
    "totalDeAvaliacoes": 480,
    "disponibilidade": 5,
    "totalDeCompras": 0,
    "ehVegetariano": false,
    "categoria": 8
  },
  {
    "codigo": 34,
    "nome": "Capuccino",
    "descricao": "Xícara pequena de café.",
    "preco": 8.3,
    "peso": 150,
    "foto": "bebida4.jpg",
    "desconto": 8.23,
    "pontosDasAvaliacoes": 4,
    "totalDeAvaliacoes": 480,
    "disponibilidade": 5,
    "totalDeCompras": 0,
    "ehVegetariano": false,
    "categoria":8
  },
  {
    "codigo": 35,
    "nome": "Coquetel de maracujá",
    "descricao": "Coquetel de vodka com maracujá.",
    "preco": 16.99,
    "peso": 150,
    "foto": "bebida5.jpg",
    "desconto": 0,
    "pontosDasAvaliacoes": 4,
    "totalDeAvaliacoes": 480,
    "disponibilidade": 5,
    "totalDeCompras": 0,
    "ehVegetariano": false,
    "categoria": 8
  }
]